classify_bills/__init__.py
classify_bills/colorlogger.py
classify_bills-1.0.1.data/data/classify_bills.config.examples/0-Example.xml
classify_bills-1.0.1.data/data/classify_bills.config.examples/Amex Blue Cash Preferred.xml
classify_bills-1.0.1.data/data/classify_bills.config.examples/Citi Mastercard.xml
classify_bills-1.0.1.data/data/classify_bills.config.examples/Con Edison.xml
classify_bills-1.0.1.data/data/classify_bills.config.examples/Time Warner Cable.xml
classify_bills-1.0.1.dist-info/LICENSE.txt
classify_bills-1.0.1.dist-info/METADATA
classify_bills-1.0.1.dist-info/WHEEL
classify_bills-1.0.1.dist-info/entry_points.txt
classify_bills-1.0.1.dist-info/top_level.txt
classify_bills-1.0.1.dist-info/RECORD
