Metadata-Version: 2.1
Name: classify-bills
Version: 1.0.1
Summary: Automatically sort and archive PDF bills and statements
Home-page: https://github.com/abelikoff/classify_bills
Author: Alexander L. Belikoff
Author-email: abelikoff@gmail.com
License: UNKNOWN
Project-URL: Bug Reports, https://github.com/abelikoff/classify_bills/issues
Project-URL: Source, https://github.com/abelikoff/classify_bills/
Keywords: bills management organize documents
Platform: UNKNOWN
Classifier: Development Status :: 5 - Production/Stable
Classifier: Environment :: Console
Classifier: Intended Audience :: End Users/Desktop
Classifier: Programming Language :: Python :: 3
Classifier: License :: OSI Approved :: GNU General Public License v3 or later (GPLv3+)
Classifier: Operating System :: OS Independent
Classifier: Topic :: Utilities
Requires-Python: >=3.5
Provides-Extra: dev
Requires-Dist: check-manifest ; extra == 'dev'
Provides-Extra: test
Requires-Dist: coverage ; extra == 'test'
